poolformer/__init__.py
poolformer/autoregressive_wrapper.py
poolformer/poolformer.py
poolformer-0.0.4.dist-info/LICENSE
poolformer-0.0.4.dist-info/METADATA
poolformer-0.0.4.dist-info/WHEEL
poolformer-0.0.4.dist-info/top_level.txt
poolformer-0.0.4.dist-info/RECORD
